llm_api_router/__init__.py
llm_api_router/client.py
llm_api_router/exceptions.py
llm_api_router/factory.py
llm_api_router/types.py
llm_api_router/providers/__init__.py
llm_api_router/providers/aliyun.py
llm_api_router/providers/anthropic.py
llm_api_router/providers/base.py
llm_api_router/providers/deepseek.py
llm_api_router/providers/gemini.py
llm_api_router/providers/openai.py
llm_api_router/providers/openrouter.py
llm_api_router/providers/xai.py
llm_api_router/providers/zhipu.py
llm_api_router-0.1.1.dist-info/METADATA
llm_api_router-0.1.1.dist-info/WHEEL
llm_api_router-0.1.1.dist-info/RECORD
