Metadata-Version: 2.4
Name: llm-api-router
Version: 0.1.1
Summary: A unified API routing library for Large Language Models
Project-URL: Homepage, https://github.com/Mikko-ww/llm-api-router
Author-email: Allen <allen125423412@163.com>
License: MIT
Requires-Python: >=3.10
Requires-Dist: httpx>=0.27.0
Requires-Dist: python-dotenv>=1.0.0
Provides-Extra: dev
Requires-Dist: mypy>=1.8.0; extra == 'dev'
Requires-Dist: pytest-asyncio>=0.23.0; extra == 'dev'
Requires-Dist: pytest>=8.0.0; extra == 'dev'
